nonebot_plugin_petpet/__init__.py
nonebot_plugin_petpet/config.py
nonebot_plugin_petpet/data_source.py
nonebot_plugin_petpet/depends.py
nonebot_plugin_petpet/download.py
nonebot_plugin_petpet/functions.py
nonebot_plugin_petpet/manager.py
nonebot_plugin_petpet/utils.py
nonebot_plugin_petpet-0.3.21.dist-info/LICENSE
nonebot_plugin_petpet-0.3.21.dist-info/METADATA
nonebot_plugin_petpet-0.3.21.dist-info/WHEEL
nonebot_plugin_petpet-0.3.21.dist-info/RECORD
