Metadata-Version: 2.1
Name: nonebot-plugin-petpet
Version: 0.3.21
Summary: Nonebot2 plugin for making fun pictures
Home-page: https://github.com/noneplugin/nonebot-plugin-petpet
License: MIT
Author: meetwq
Author-email: meetwq@gmail.com
Requires-Python: >=3.8,<4.0
Classifier: License :: OSI Approved :: MIT License
Classifier: Programming Language :: Python :: 3
Classifier: Programming Language :: Python :: 3.8
Classifier: Programming Language :: Python :: 3.9
Classifier: Programming Language :: Python :: 3.10
Classifier: Programming Language :: Python :: 3.11
Requires-Dist: Pillow (>=9.0.0,<10.0.0)
Requires-Dist: httpx (>=0.19.0)
Requires-Dist: nonebot-adapter-onebot (>=2.1.1,<3.0.0)
Requires-Dist: nonebot-plugin-imageutils (>=0.1.14,<0.2.0)
Requires-Dist: nonebot2[fastapi] (>=2.0.0-rc.1,<3.0.0)
Project-URL: Repository, https://github.com/noneplugin/nonebot-plugin-petpet
